kengine/__init__.py
kengine/agent/__init__.py
kengine/agent/shared/__init__.py
kengine/agent/shared/callbacks.py
kengine/agent/shared/decorators.py
kengine/agent/shared/executor_factory.py
kengine/agent/shared/multi_action_parser.py
kengine/agent/shared/outputparser.py
kengine/agent/shared/tools/__init__.py
kengine/agent/shared/tools/base.py
kengine/agent/shared/tools/code_skeleton_tool.py
kengine/agent/shared/tools/db_extractor_tool.py
kengine/agent/shared/tools/dependency_extractor_tool.py
kengine/agent/shared/tools/directory_structure.py
kengine/agent/shared/tools/error_handler.py
kengine/agent/shared/tools/exceptions.py
kengine/agent/shared/tools/factory.py
kengine/agent/shared/tools/file_read.py
kengine/agent/shared/tools/file_search.py
kengine/agent/shared/tools/method_dependency_analyzer.py
kengine/agent/shared/tools/method_extractor_tool.py
kengine/agent/shared/tools/prd_review_tools.py
kengine/agent/shared/tools/rag_search.py
kengine/agent/shared/tools/text_grep_tool.py
kengine/cache/__init__.py
kengine/cache/manager.py
kengine/chat/__init__.py
kengine/chat/agent_cli.py
kengine/chat/ask_chat_service.py
kengine/chat/base_agent_chat_service.py
kengine/chat/cli.py
kengine/chat/components.py
kengine/chat/conversion.py
kengine/chat/models.py
kengine/chat/prd_review_service.py
kengine/chat/protocols.py
kengine/chat/server.py
kengine/chat/service.py
kengine/cli/__init__.py
kengine/cli/cli.py
kengine/code/__init__.py
kengine/code/language_loader.py
kengine/code/utils.py
kengine/code/reader/__init__.py
kengine/code/reader/dependency_extractor.py
kengine/code/reader/method_extractor.py
kengine/code/reader/dependency_analyzer/__init__.py
kengine/code/reader/dependency_analyzer/ast_parser.py
kengine/code/reader/dependency_analyzer/java_method_analyzer.py
kengine/code/reader/dependency_analyzer/models.py
kengine/code/reader/parsers/__init__.py
kengine/code/reader/parsers/base_parser.py
kengine/code/reader/parsers/c_parser.py
kengine/code/reader/parsers/cpp_parser.py
kengine_mcp_server-0.1.2.dist-info/licenses/LICENSE
kengine_mcp_server-0.1.2.dist-info/METADATA
kengine_mcp_server-0.1.2.dist-info/WHEEL
kengine_mcp_server-0.1.2.dist-info/entry_points.txt
kengine_mcp_server-0.1.2.dist-info/top_level.txt
kengine_mcp_server-0.1.2.dist-info/RECORD
