Metadata-Version: 2.4
Name: kengine-mcp-server
Version: 0.1.2
Summary: MCP (Model Context Protocol) server for knowledge engineering
Home-page: https://github.com/your-organization/knowledge-engineering
Author: Knowledge Engineering Team
Author-email: your.email@example.com
Classifier: Programming Language :: Python :: 3
Classifier: License :: OSI Approved :: MIT License
Classifier: Operating System :: OS Independent
Requires-Python: >=3.8
License-File: LICENSE
Requires-Dist: requests>=2.25.0
Requires-Dist: langchain>=0.0.267
Requires-Dist: langchain-core>=0.1.0
Requires-Dist: numpy>=1.24.0
Requires-Dist: aiohttp>=3.12.0
Requires-Dist: anthropic>=0.59.0
Requires-Dist: faiss-cpu>=1.8.0
Requires-Dist: flask>=3.0.0
Requires-Dist: flask-cors>=4.0.0
Requires-Dist: langchain-anthropic>=0.3.0
Requires-Dist: langchain-community>=0.3.0
Requires-Dist: langchain-openai>=0.2.0
Requires-Dist: openai>=1.97.0
Requires-Dist: pydantic>=2.11.0
Requires-Dist: python-dotenv>=1.1.0
Requires-Dist: pyyaml>=6.0.0
Requires-Dist: tiktoken>=0.9.0
Requires-Dist: pymysql>=1.1.0
Requires-Dist: dataclasses-json>=0.5.0
Requires-Dist: boto3<=1.35.99
Dynamic: author
Dynamic: author-email
Dynamic: classifier
Dynamic: description
Dynamic: description-content-type
Dynamic: home-page
Dynamic: license-file
Dynamic: requires-dist
Dynamic: requires-python
Dynamic: summary
